pyDataVis/__init__.py
pyDataVis/convCIF.py
pyDataVis/convIso.py
pyDataVis/convert.py
pyDataVis/dataTable.py
pyDataVis/main.py
pyDataVis/plotWindow.py
pyDataVis/pyDataVis.py
pyDataVis/script.py
pyDataVis/tests.py
pyDataVis/toolsDialogs.py
pyDataVis/utils.py
pyDataVis-1.5.0.dist-info/LICENSE
pyDataVis-1.5.0.dist-info/METADATA
pyDataVis-1.5.0.dist-info/WHEEL
pyDataVis-1.5.0.dist-info/entry_points.txt
pyDataVis-1.5.0.dist-info/top_level.txt
pyDataVis-1.5.0.dist-info/RECORD
