Metadata-Version: 2.1
Name: pyDataVis
Version: 1.5.0
Summary: A GUI application for fast visualization and analysis of numerical data
Home-page: https://github.com/PierreAlphonse/pyDataVis.git
Author: Pierre Alphonse
Author-email: palphonse@wanadoo.fr
License: MIT
Platform: UNKNOWN
Classifier: Programming Language :: Python :: 3
Classifier: License :: OSI Approved :: MIT License
Classifier: Operating System :: OS Independent
Classifier: Intended Audience :: Science/Research
Classifier: Topic :: Scientific/Engineering :: Visualization
Requires-Dist: pandas
Requires-Dist: scipy
Requires-Dist: matplotlib
Requires-Dist: PyQt5
Requires-Dist: odfpy
Requires-Dist: dans-diffraction
